dracula/__init__.py
dracula/__main__.py
dracula/_cli.py
dracula/_colors.py
dracula/_downloader.py
dracula/_tui.py
dracula/_typer.py
dracula/_utils.py
dracula_cli-0.1.2.dist-info/LICENSE
dracula_cli-0.1.2.dist-info/METADATA
dracula_cli-0.1.2.dist-info/WHEEL
dracula_cli-0.1.2.dist-info/entry_points.txt
dracula_cli-0.1.2.dist-info/top_level.txt
dracula_cli-0.1.2.dist-info/RECORD
