Metadata-Version: 2.1
Name: dracula-cli
Version: 0.1.2
Summary: A beautiful command line interface for draculatheme.org and dracula in general
Home-page: https://github.com/dracula/dracula-cli
Author: Wasi Master
Author-email: arianmollik323@gmail.com
License: MIT
Project-URL: Bug Tracker, https://github.com/dracula/dracula-cli/issues
Project-URL: Source, https://github.com/dracula/dracula-cli
Project-URL: Say Thanks, https://saythanks.io/to/wasi-master
Keywords: dracula,dracula-cli,dracula-theme,python-dracula
Platform: UNKNOWN
Classifier: Development Status :: 5 - Production/Stable
Classifier: Environment :: Console
Classifier: Intended Audience :: Developers
Classifier: Intended Audience :: End Users/Desktop
Classifier: License :: OSI Approved :: MIT License
Classifier: Natural Language :: English
Classifier: Operating System :: OS Independent
Classifier: Programming Language :: Python :: 3
Classifier: Programming Language :: Python :: 3 :: Only
Classifier: Programming Language :: Python :: 3.6
Classifier: Programming Language :: Python :: 3.7
Classifier: Programming Language :: Python :: 3.8
Classifier: Programming Language :: Python :: 3.9
Classifier: Programming Language :: Python :: 3.10
Classifier: Topic :: Terminals
Requires-Python: >=3.6
License-File: LICENSE
Requires-Dist: rich
Requires-Dist: typer
Requires-Dist: requests-cache
Requires-Dist: rich-click
Requires-Dist: humanize
Requires-Dist: thefuzz
Requires-Dist: textual
Requires-Dist: textual-inputs (==0.2.*)
Requires-Dist: rapidfuzz
Requires-Dist: questionary
